axp_tools/__init__.py
axp_tools/axp2img.py
axp_tools/version.py
axp_tools-1.0.2.dist-info/licenses/LICENSE
axp_tools-1.0.2.dist-info/METADATA
axp_tools-1.0.2.dist-info/WHEEL
axp_tools-1.0.2.dist-info/entry_points.txt
axp_tools-1.0.2.dist-info/top_level.txt
axp_tools-1.0.2.dist-info/RECORD
